{"url":"http://happia.ru/","runs":1,"browserName":"firefox","browserVersion":"43.0.4","platform":"Linux","browserTimeVersion":"0.12.2","default":{"statistics":{"domainLookupTime":{"min":"0","max":"0","p10":"0","p70":"0","p80":"0","p90":"0","p99":"0","median":"0","mean":"0"},"redirectionTime":{"min":"1","max":"1","p10":"1","p70":"1","p80":"1","p90":"1","p99":"1","median":"1","mean":"1"},"serverConnectionTime":{"min":"0","max":"0","p10":"0","p70":"0","p80":"0","p90":"0","p99":"0","median":"0","mean":"0"},"serverResponseTime":{"min":"795","max":"795","p10":"795","p70":"795","p80":"795","p90":"795","p99":"795","median":"795","mean":"795"},"pageDownloadTime":{"min":"509","max":"509","p10":"509","p70":"509","p80":"509","p90":"509","p99":"509","median":"509","mean":"509"},"domInteractiveTime":{"min":"3049","max":"3049","p10":"3049","p70":"3049","p80":"3049","p90":"3049","p99":"3049","median":"3049","mean":"3049"},"domContentLoadedTime":{"min":"3142","max":"3142","p10":"3142","p70":"3142","p80":"3142","p90":"3142","p99":"3142","median":"3142","mean":"3142"},"pageLoadTime":{"min":"6238","max":"6238","p10":"6238","p70":"6238","p80":"6238","p90":"6238","p99":"6238","median":"6238","mean":"6238"},"frontEndTime":{"min":"5442","max":"5442","p10":"5442","p70":"5442","p80":"5442","p90":"5442","p99":"5442","median":"5442","mean":"5442"},"backEndTime":{"min":"287","max":"287","p10":"287","p70":"287","p80":"287","p90":"287","p99":"287","median":"287","mean":"287"},"documentHeight":{"min":"3316","max":"3316","p10":"3316","p70":"3316","p80":"3316","p90":"3316","p99":"3316","median":"3316","mean":"3316"},"documentWidth":{"min":"1264","max":"1264","p10":"1264","p70":"1264","p80":"1264","p90":"1264","p99":"1264","median":"1264","mean":"1264"},"firstPaint":{"min":"2831","max":"2831","p10":"2831","p70":"2831","p80":"2831","p90":"2831","p99":"2831","median":"2831","mean":"2831"},"fetchStart":{"min":"1","max":"1","p10":"1","p70":"1","p80":"1","p90":"1","p99":"1","median":"1","mean":"1"},"domainLookupStart":{"min":"1","max":"1","p10":"1","p70":"1","p80":"1","p90":"1","p99":"1","median":"1","mean":"1"},"domainLookupEnd":{"min":"1","max":"1","p10":"1","p70":"1","p80":"1","p90":"1","p99":"1","median":"1","mean":"1"},"connectStart":{"min":"1","max":"1","p10":"1","p70":"1","p80":"1","p90":"1","p99":"1","median":"1","mean":"1"},"connectEnd":{"min":"1","max":"1","p10":"1","p70":"1","p80":"1","p90":"1","p99":"1","median":"1","mean":"1"},"requestStart":{"min":"1","max":"1","p10":"1","p70":"1","p80":"1","p90":"1","p99":"1","median":"1","mean":"1"},"responseStart":{"min":"287","max":"287","p10":"287","p70":"287","p80":"287","p90":"287","p99":"287","median":"287","mean":"287"},"responseEnd":{"min":"796","max":"796","p10":"796","p70":"796","p80":"796","p90":"796","p99":"796","median":"796","mean":"796"},"domLoading":{"min":"289","max":"289","p10":"289","p70":"289","p80":"289","p90":"289","p99":"289","median":"289","mean":"289"},"domInteractive":{"min":"3049","max":"3049","p10":"3049","p70":"3049","p80":"3049","p90":"3049","p99":"3049","median":"3049","mean":"3049"},"domContentLoadedEventStart":{"min":"3142","max":"3142","p10":"3142","p70":"3142","p80":"3142","p90":"3142","p99":"3142","median":"3142","mean":"3142"},"domContentLoadedEventEnd":{"min":"3332","max":"3332","p10":"3332","p70":"3332","p80":"3332","p90":"3332","p99":"3332","median":"3332","mean":"3332"},"domComplete":{"min":"6238","max":"6238","p10":"6238","p70":"6238","p80":"6238","p90":"6238","p99":"6238","median":"6238","mean":"6238"},"loadEventStart":{"min":"6238","max":"6238","p10":"6238","p70":"6238","p80":"6238","p90":"6238","p99":"6238","median":"6238","mean":"6238"},"loadEventEnd":{"min":"6242","max":"6242","p10":"6242","p70":"6242","p80":"6242","p90":"6242","p99":"6242","median":"6242","mean":"6242"},"speedIndex":{"min":"4490","max":"4490","p10":"4490","p70":"4490","p80":"4490","p90":"4490","p99":"4490","median":"4490","mean":"4490"}},"data":[{"documentHeight":3316,"documentTitle":"Магазин «Хаппиа» - костюмы на Хэллоуин, маски, грим, акссессуары, линзы, украшения для Хэллоуина в Москве и Санкт-Петербурге","documentWidth":1264,"firstPaint":2831.0359799999997,"navigationTiming":{"navigationStart":0,"unloadEventStart":0,"unloadEventEnd":0,"redirectStart":0,"redirectEnd":0,"fetchStart":1,"domainLookupStart":1,"domainLookupEnd":1,"connectStart":1,"connectEnd":1,"secureConnectionStart":null,"requestStart":1,"responseStart":287,"responseEnd":796,"domLoading":289,"domInteractive":3049,"domContentLoadedEventStart":3142,"domContentLoadedEventEnd":3332,"domComplete":6238,"loadEventStart":6238,"loadEventEnd":6242},"resourceTimings":[{"initiatorType":"link","redirectStart":0,"redirectEnd":0,"fetchStart":318.133363,"domainLookupStart":318.133363,"domainLookupEnd":318.133363,"connectStart":318.133363,"connectEnd":318.133363,"secureConnectionStart":0,"requestStart":318.868472,"responseStart":398.046745,"responseEnd":398.09081699999996,"name":"http://fonts.googleapis.com/css?family=PT+Sans:400,700,400italic,700italic&subset=latin,cyrillic","entryType":"resource","startTime":318.133363,"duration":79.95745399999998},{"initiatorType":"script","redirectStart":0,"redirectEnd":0,"fetchStart":319.068182,"domainLookupStart":319.068182,"domainLookupEnd":319.068182,"connectStart":319.068182,"connectEnd":319.068182,"secureConnectionStart":0,"requestStart":319.55011,"responseStart":614.11096,"responseEnd":2831.0359799999997,"name":"http://happia.ru/media/js/da0c37aa8bb5cee5d7b8fc5092bea21b.js","entryType":"resource","startTime":319.068182,"duration":2511.9677979999997},{"initiatorType":"link","redirectStart":0,"redirectEnd":0,"fetchStart":319.747682,"domainLookupStart":319.747682,"domainLookupEnd":319.747682,"connectStart":319.747682,"connectEnd":319.747682,"secureConnectionStart":0,"requestStart":320.20078,"responseStart":646.933714,"responseEnd":646.984794,"name":"http://happia.ru/media/css/d5f4c859dfa1b566494c8eb5e03c9f48.css","entryType":"resource","startTime":319.747682,"duration":327.23711199999997},{"initiatorType":"link","redirectStart":0,"redirectEnd":0,"fetchStart":320.400916,"domainLookupStart":320.400916,"domainLookupEnd":320.400916,"connectStart":320.400916,"connectEnd":320.400916,"secureConnectionStart":0,"requestStart":320.852011,"responseStart":651.093161,"responseEnd":1343.316842,"name":"http://happia.ru/media/css/b97fedead73a1143b669bd903b8401c7.css","entryType":"resource","startTime":320.400916,"duration":1022.9159259999999},{"initiatorType":"link","redirectStart":0,"redirectEnd":0,"fetchStart":321.051316,"domainLookupStart":321.051316,"domainLookupEnd":321.051316,"connectStart":321.051316,"connectEnd":321.051316,"secureConnectionStart":0,"requestStart":321.775345,"responseStart":647.015392,"responseEnd":647.029068,"name":"http://happia.ru/media/css/94c79042a63d796d107b2319ac3d2fd7.css","entryType":"resource","startTime":321.051316,"duration":325.97775200000007},{"initiatorType":"img","redirectStart":0,"redirectEnd":0,"fetchStart":322.005589,"domainLookupStart":322.005589,"domainLookupEnd":322.005589,"connectStart":322.005589,"connectEnd":322.005589,"secureConnectionStart":0,"requestStart":2831.126857,"responseStart":3112.000657,"responseEnd":4480.783073,"name":"http://happia.ru/media/mygento/hcp/revolution/features_05_1.jpg","entryType":"resource","startTime":322.005589,"duration":4158.777483999999},{"initiatorType":"img","redirectStart":0,"redirectEnd":0,"fetchStart":323.373343,"domainLookupStart":323.373343,"domainLookupEnd":323.373343,"connectStart":323.373343,"connectEnd":323.373343,"secureConnectionStart":0,"requestStart":2831.174812,"responseStart":2980.814906,"responseEnd":2980.855638,"name":"http://happia.ru/media/queldorei/shopper/revolution/grim.png","entryType":"resource","startTime":323.373343,"duration":2657.482295},{"initiatorType":"img","redirectStart":0,"redirectEnd":0,"fetchStart":323.528336,"domainLookupStart":323.528336,"domainLookupEnd":323.528336,"connectStart":323.528336,"connectEnd":323.528336,"secureConnectionStart":0,"requestStart":2831.243013,"responseStart":2979.61076,"responseEnd":3117.854834,"name":"http://happia.ru/media/queldorei/shopper/revolution/grim2.png","entryType":"resource","startTime":323.528336,"duration":2794.3264980000004},{"initiatorType":"img","redirectStart":0,"redirectEnd":0,"fetchStart":323.69671700000004,"domainLookupStart":323.69671700000004,"domainLookupEnd":323.69671700000004,"connectStart":323.69671700000004,"connectEnd":323.69671700000004,"secureConnectionStart":0,"requestStart":2831.287718,"responseStart":2979.719775,"responseEnd":4502.750984,"name":"http://happia.ru/media/mygento/hcp/revolution/features_02_1.jpg","entryType":"resource","startTime":323.69671700000004,"duration":4179.054267},{"initiatorType":"img","redirectStart":0,"redirectEnd":0,"fetchStart":323.850818,"domainLookupStart":323.850818,"domainLookupEnd":323.850818,"connectStart":323.850818,"connectEnd":323.850818,"secureConnectionStart":0,"requestStart":2831.330361,"responseStart":2977.7574489999997,"responseEnd":4502.726012,"name":"http://happia.ru/media/mygento/hcp/revolution/unique_magento_theme_1.jpg","entryType":"resource","startTime":323.850818,"duration":4178.875194},{"initiatorType":"img","redirectStart":0,"redirectEnd":0,"fetchStart":348.92593999999997,"domainLookupStart":348.92593999999997,"domainLookupEnd":348.92593999999997,"connectStart":348.92593999999997,"connectEnd":348.92593999999997,"secureConnectionStart":0,"requestStart":2831.377716,"responseStart":2989.767153,"responseEnd":3114.484033,"name":"http://happia.ru/media/product/75/novogodnii-kostyum-santa-klausa-dlya-malyshki-28.jpg","entryType":"resource","startTime":348.92593999999997,"duration":2765.558093},{"initiatorType":"img","redirectStart":0,"redirectEnd":0,"fetchStart":349.748157,"domainLookupStart":349.748157,"domainLookupEnd":349.748157,"connectStart":349.748157,"connectEnd":349.748157,"secureConnectionStart":0,"requestStart":2831.425205,"responseStart":2979.674988,"responseEnd":2979.701697,"name":"http://happia.ru/media/product/93/detskii-kostyum-betmena-12.jpg","entryType":"resource","startTime":349.748157,"duration":2629.95354},{"initiatorType":"img","redirectStart":0,"redirectEnd":0,"fetchStart":350.29403199999996,"domainLookupStart":350.29403199999996,"domainLookupEnd":350.29403199999996,"connectStart":350.29403199999996,"connectEnd":350.29403199999996,"secureConnectionStart":0,"requestStart":2831.483616,"responseStart":2977.670064,"responseEnd":2977.7232320000003,"name":"http://happia.ru/media/product/e7/kosa-snegurochki-76.jpg","entryType":"resource","startTime":350.29403199999996,"duration":2627.4292000000005},{"initiatorType":"img","redirectStart":0,"redirectEnd":0,"fetchStart":350.835567,"domainLookupStart":350.835567,"domainLookupEnd":350.835567,"connectStart":350.835567,"connectEnd":350.835567,"secureConnectionStart":0,"requestStart":2831.777251,"responseStart":3121.178011,"responseEnd":3478.7037889999997,"name":"http://happia.ru/media/product/2d/muzhskoi-kostyum-zorro-a5.jpg","entryType":"resource","startTime":350.835567,"duration":3127.8682219999996},{"initiatorType":"img","redirectStart":0,"redirectEnd":0,"fetchStart":351.958502,"domainLookupStart":2831.8409540000002,"domainLookupEnd":2838.558076,"connectStart":2838.577639,"connectEnd":2841.520591,"secureConnectionStart":0,"requestStart":2842.316776,"responseStart":3168.171178,"responseEnd":3976.81066,"name":"http://happia.ru/media/wysiwyg/phoneorder.jpg","entryType":"resource","startTime":351.958502,"duration":3624.852158},{"initiatorType":"img","redirectStart":0,"redirectEnd":0,"fetchStart":352.506303,"domainLookupStart":2831.851533,"domainLookupEnd":2838.664997,"connectStart":2838.679333,"connectEnd":2841.511036,"secureConnectionStart":0,"requestStart":2842.273992,"responseStart":3230.081902,"responseEnd":3988.322928,"name":"http://happia.ru/media/wysiwyg/delivery.jpg","entryType":"resource","startTime":352.506303,"duration":3635.816625},{"initiatorType":"img","redirectStart":0,"redirectEnd":0,"fetchStart":353.047113,"domainLookupStart":2831.861707,"domainLookupEnd":2838.73144,"connectStart":2838.745186,"connectEnd":2841.50059,"secureConnectionStart":0,"requestStart":2842.2306970000004,"responseStart":3222.779338,"responseEnd":3985.92092,"name":"http://happia.ru/media/wysiwyg/docs.jpg","entryType":"resource","startTime":353.047113,"duration":3632.873807},{"initiatorType":"img","redirectStart":0,"redirectEnd":0,"fetchStart":353.584998,"domainLookupStart":2831.871432,"domainLookupEnd":2838.794065,"connectStart":2838.8069859999996,"connectEnd":2841.4909970000003,"secureConnectionStart":0,"requestStart":2842.187949,"responseStart":3226.3873470000003,"responseEnd":3977.9113389999998,"name":"http://happia.ru/media/wysiwyg/on-hold.jpg","entryType":"resource","startTime":353.584998,"duration":3624.326341},{"initiatorType":"img","redirectStart":0,"redirectEnd":0,"fetchStart":354.128688,"domainLookupStart":2831.8804320000004,"domainLookupEnd":2839.131714,"connectStart":2839.147958,"connectEnd":2841.481298,"secureConnectionStart":0,"requestStart":2842.143588,"responseStart":3232.70544,"responseEnd":3232.738198,"name":"http://happia.ru/media/wysiwyg/suppliers/andrea.gif","entryType":"resource","startTime":354.128688,"duration":2878.6095100000002},{"initiatorType":"img","redirectStart":0,"redirectEnd":0,"fetchStart":354.66454,"domainLookupStart":2831.8895039999998,"domainLookupEnd":2839.2234529999996,"connectStart":2839.236149,"connectEnd":2841.470542,"secureConnectionStart":0,"requestStart":2842.0986909999997,"responseStart":3335.2896379999997,"responseEnd":3483.6571360000003,"name":"http://happia.ru/media/wysiwyg/suppliers/wilberskarnaval.jpg","entryType":"resource","startTime":354.66454,"duration":3128.992596},{"initiatorType":"img","redirectStart":0,"redirectEnd":0,"fetchStart":355.219493,"domainLookupStart":2831.899156,"domainLookupEnd":2839.287932,"connectStart":2839.300276,"connectEnd":2841.46066,"secureConnectionStart":0,"requestStart":2842.048139,"responseStart":3234.731902,"responseEnd":3234.7666670000003,"name":"http://happia.ru/media/wysiwyg/suppliers/rubies.jpg","entryType":"resource","startTime":355.219493,"duration":2879.5471740000003},{"initiatorType":"img","redirectStart":0,"redirectEnd":0,"fetchStart":355.758025,"domainLookupStart":2831.909946,"domainLookupEnd":2839.350204,"connectStart":2839.365473,"connectEnd":2841.449545,"secureConnectionStart":0,"requestStart":2842.003905,"responseStart":3238.824459,"responseEnd":3238.8630080000003,"name":"http://happia.ru/media/wysiwyg/suppliers/grimtout.jpg","entryType":"resource","startTime":355.758025,"duration":2883.104983},{"initiatorType":"img","redirectStart":0,"redirectEnd":0,"fetchStart":356.302754,"domainLookupStart":2831.920061,"domainLookupEnd":2839.4151650000003,"connectStart":2839.428075,"connectEnd":2841.439789,"secureConnectionStart":0,"requestStart":2841.961055,"responseStart":3276.6655889999997,"responseEnd":3276.7154330000003,"name":"http://happia.ru/media/wysiwyg/suppliers/brandxlatex.jpg","entryType":"resource","startTime":356.302754,"duration":2920.4126790000005},{"initiatorType":"img","redirectStart":0,"redirectEnd":0,"fetchStart":356.846886,"domainLookupStart":2831.9298590000003,"domainLookupEnd":2839.474449,"connectStart":2839.4885099999997,"connectEnd":2841.429786,"secureConnectionStart":0,"requestStart":2841.9166680000003,"responseStart":3241.620015,"responseEnd":3241.6544470000003,"name":"http://happia.ru/media/wysiwyg/suppliers/colorvue.jpg","entryType":"resource","startTime":356.846886,"duration":2884.8075610000005},{"initiatorType":"img","redirectStart":0,"redirectEnd":0,"fetchStart":357.38077699999997,"domainLookupStart":2831.939836,"domainLookupEnd":2839.5379319999997,"connectStart":2839.55152,"connectEnd":2841.41863,"secureConnectionStart":0,"requestStart":2841.8701340000002,"responseStart":3234.867877,"responseEnd":3234.903237,"name":"http://happia.ru/media/wysiwyg/clients/sber.jpg","entryType":"resource","startTime":357.38077699999997,"duration":2877.52246},{"initiatorType":"img","redirectStart":0,"redirectEnd":0,"fetchStart":357.91233700000004,"domainLookupStart":2831.949542,"domainLookupEnd":2839.597808,"connectStart":2839.6106419999996,"connectEnd":2841.40061,"secureConnectionStart":0,"requestStart":2841.825931,"responseStart":3286.330714,"responseEnd":3286.365468,"name":"http://happia.ru/media/wysiwyg/clients/yahonty.jpg","entryType":"resource","startTime":357.91233700000004,"duration":2928.4531309999998},{"initiatorType":"img","redirectStart":0,"redirectEnd":0,"fetchStart":358.450113,"domainLookupStart":2831.959184,"domainLookupEnd":2839.656625,"connectStart":2839.6685310000003,"connectEnd":2839.970379,"secureConnectionStart":0,"requestStart":2841.780266,"responseStart":3242.403796,"responseEnd":3242.484302,"name":"http://happia.ru/media/wysiwyg/clients/mh.gif","entryType":"resource","startTime":358.450113,"duration":2884.034189},{"initiatorType":"img","redirectStart":0,"redirectEnd":0,"fetchStart":358.987807,"domainLookupStart":2831.968735,"domainLookupEnd":2839.7145309999996,"connectStart":2839.726667,"connectEnd":2839.959996,"secureConnectionStart":0,"requestStart":2841.7340090000002,"responseStart":3284.579669,"responseEnd":3284.622286,"name":"http://happia.ru/media/wysiwyg/clients/rdd.png","entryType":"resource","startTime":358.987807,"duration":2925.634479},{"initiatorType":"img","redirectStart":0,"redirectEnd":0,"fetchStart":359.54846299999997,"domainLookupStart":2831.9775059999997,"domainLookupEnd":2839.772082,"connectStart":2839.786054,"connectEnd":2839.947908,"secureConnectionStart":0,"requestStart":2841.6889969999997,"responseStart":3338.636052,"responseEnd":3476.850404,"name":"http://happia.ru/media/wysiwyg/clients/balagan.jpg","entryType":"resource","startTime":359.54846299999997,"duration":3117.3019409999997},{"initiatorType":"img","redirectStart":0,"redirectEnd":0,"fetchStart":536.7180940000001,"domainLookupStart":2831.987631,"domainLookupEnd":2839.832331,"connectStart":2839.8453560000003,"connectEnd":2839.927948,"secureConnectionStart":0,"requestStart":2841.638671,"responseStart":3277.2409589999997,"responseEnd":3489.708665,"name":"http://happia.ru/skin/frontend/default/hcp/images/happia.jpg","entryType":"resource","startTime":536.7180940000001,"duration":2952.9905710000003},{"initiatorType":"script","redirectStart":0,"redirectEnd":0,"fetchStart":3012.8633480000003,"domainLookupStart":0,"domainLookupEnd":0,"connectStart":0,"connectEnd":0,"secureConnectionStart":0,"requestStart":0,"responseStart":0,"responseEnd":3098.137646,"name":"http://www.google-analytics.com/ga.js","entryType":"resource","startTime":3012.8633480000003,"duration":85.27429799999982},{"initiatorType":"subdocument","redirectStart":0,"redirectEnd":0,"fetchStart":3443.402427,"domainLookupStart":0,"domainLookupEnd":0,"connectStart":0,"connectEnd":0,"secureConnectionStart":0,"requestStart":0,"responseStart":0,"responseEnd":4612.43866,"name":"http://www.youtube.com/embed/tfIPiGoXcNk","entryType":"resource","startTime":3041.6016250000002,"duration":1570.8370349999996},{"initiatorType":"script","redirectStart":0,"redirectEnd":0,"fetchStart":3506.6491530000003,"domainLookupStart":0,"domainLookupEnd":0,"connectStart":0,"connectEnd":0,"secureConnectionStart":0,"requestStart":0,"responseStart":0,"responseEnd":4708.798659,"name":"http://mc.yandex.ru/metrika/watch.js","entryType":"resource","startTime":3048.0232140000003,"duration":1660.7754449999998},{"initiatorType":"xmlhttprequest","redirectStart":0,"redirectEnd":0,"fetchStart":3049.629306,"domainLookupStart":3049.629306,"domainLookupEnd":3049.629306,"connectStart":3049.629306,"connectEnd":3049.629306,"secureConnectionStart":0,"requestStart":3050.399895,"responseStart":3193.037151,"responseEnd":3193.112666,"name":"http://happia.ru/turpentine/esi/getBlock/method/ajax/access/public/ttl/72000/hmac/57a8a067ad2980e8b4eaf01dc1dea2013896454b7c8edd729bf18b28b269babc/data/cEI4cqyyx6HKviydQet5YmyhMpaLmBMxwxQvaLuGPgS4rthnK15644vQKTxkcFsbLbg7wa-DFBZ4ErU9d0sGQbN3d6RImbqlH6akuqlygxQxRL2TvzjjNQ3uCxPJk2QdDzRhyvAUSl.XfSwJv3viBnc9XYTtVLrTxi03nMF5SbkuOPjvqNr-eUVTSoowF52UOX0OGCOBsZY0v39Xx-7APK9g3IAgFUXGX5t4eWGQiGjqajuTeoFrDRAhj4VBnR0qWx-3krz0R8I2frUcZXOPWw==/","entryType":"resource","startTime":3049.629306,"duration":143.48336000000018},{"initiatorType":"css","redirectStart":0,"redirectEnd":0,"fetchStart":3053.053989,"domainLookupStart":3053.053989,"domainLookupEnd":3053.053989,"connectStart":3053.053989,"connectEnd":3053.053989,"secureConnectionStart":0,"requestStart":3053.4562109999997,"responseStart":3225.455982,"responseEnd":3225.492472,"name":"http://happia.ru/skin/frontend/default/hcp/images/ico-shoppolicy.png","entryType":"resource","startTime":3053.053989,"duration":172.4384829999999},{"initiatorType":"css","redirectStart":0,"redirectEnd":0,"fetchStart":3055.387234,"domainLookupStart":3055.387234,"domainLookupEnd":3055.387234,"connectStart":3055.387234,"connectEnd":3055.387234,"secureConnectionStart":0,"requestStart":3055.73263,"responseStart":3224.5701320000003,"responseEnd":3224.603675,"name":"http://happia.ru/skin/frontend/default/hcp/images/news_bg_06.png","entryType":"resource","startTime":3055.387234,"duration":169.21644100000003},{"initiatorType":"css","redirectStart":0,"redirectEnd":0,"fetchStart":3055.988616,"domainLookupStart":3055.988616,"domainLookupEnd":3055.988616,"connectStart":3055.988616,"connectEnd":3055.988616,"secureConnectionStart":0,"requestStart":3056.3261709999997,"responseStart":3492.8409540000002,"responseEnd":3492.877237,"name":"http://happia.ru/skin/frontend/default/hcp/images/arrow-nav.png","entryType":"resource","startTime":3055.988616,"duration":436.88862100000006},{"initiatorType":"css","redirectStart":0,"redirectEnd":0,"fetchStart":3058.1052569999997,"domainLookupStart":3058.1052569999997,"domainLookupEnd":3058.1052569999997,"connectStart":3058.1052569999997,"connectEnd":3058.1052569999997,"secureConnectionStart":0,"requestStart":3058.458823,"responseStart":3361.6656479999997,"responseEnd":3497.734837,"name":"http://happia.ru/skin/frontend/default/hcp/images/sprite.png","entryType":"resource","startTime":3058.1052569999997,"duration":439.62958000000026},{"initiatorType":"css","redirectStart":0,"redirectEnd":0,"fetchStart":3058.9560859999997,"domainLookupStart":3058.9560859999997,"domainLookupEnd":3058.9560859999997,"connectStart":3058.9560859999997,"connectEnd":3058.9560859999997,"secureConnectionStart":0,"requestStart":3059.323945,"responseStart":3483.675957,"responseEnd":3483.707119,"name":"http://happia.ru/skin/frontend/default/hcp/images/arrow3.png","entryType":"resource","startTime":3058.9560859999997,"duration":424.75103300000046},{"initiatorType":"css","redirectStart":0,"redirectEnd":0,"fetchStart":3064.961353,"domainLookupStart":3064.961353,"domainLookupEnd":3064.961353,"connectStart":3064.961353,"connectEnd":3064.961353,"secureConnectionStart":0,"requestStart":3065.341955,"responseStart":3478.734897,"responseEnd":3478.781594,"name":"http://happia.ru/skin/frontend/default/hcp/images/srchloop.png","entryType":"resource","startTime":3064.961353,"duration":413.8202409999999},{"initiatorType":"other","redirectStart":0,"redirectEnd":0,"fetchStart":3080.542316,"domainLookupStart":3080.542316,"domainLookupEnd":3080.542316,"connectStart":3080.542316,"connectEnd":3080.542316,"secureConnectionStart":0,"requestStart":3081.156098,"responseStart":3513.9890299999997,"responseEnd":3980.7033939999997,"name":"http://fonts.gstatic.com/s/ptsans/v8/BJVWev7_auVaQ__OU8QihwLUuEpTyoUstqEm5AMlJo4.woff2","entryType":"resource","startTime":3080.542316,"duration":900.1610779999996},{"initiatorType":"other","redirectStart":0,"redirectEnd":0,"fetchStart":3085.196826,"domainLookupStart":3085.196826,"domainLookupEnd":3085.196826,"connectStart":3085.196826,"connectEnd":3085.196826,"secureConnectionStart":0,"requestStart":3088.8960079999997,"responseStart":3513.201616,"responseEnd":3983.527713,"name":"http://fonts.gstatic.com/s/ptsans/v8/g46X4VH_KHOWAAa-HpnGPgzyDMXhdD8sAj6OAJTFsBI.woff2","entryType":"resource","startTime":3085.196826,"duration":898.3308870000001},{"initiatorType":"xmlhttprequest","redirectStart":0,"redirectEnd":0,"fetchStart":3150.339632,"domainLookupStart":3150.339632,"domainLookupEnd":3150.339632,"connectStart":3150.339632,"connectEnd":3150.339632,"secureConnectionStart":0,"requestStart":3150.578571,"responseStart":3692.859019,"responseEnd":3692.925009,"name":"http://happia.ru/xwarehouse/index/initWarehouse","entryType":"resource","startTime":3150.339632,"duration":542.5853769999999},{"initiatorType":"css","redirectStart":0,"redirectEnd":0,"fetchStart":3261.570774,"domainLookupStart":3261.570774,"domainLookupEnd":3261.570774,"connectStart":3261.570774,"connectEnd":3261.570774,"secureConnectionStart":0,"requestStart":3261.77325,"responseStart":3651.522821,"responseEnd":3651.581353,"name":"http://happia.ru/skin/frontend/default/hcp/images/loader.gif","entryType":"resource","startTime":3261.570774,"duration":390.01057900000023},{"initiatorType":"img","redirectStart":0,"redirectEnd":0,"fetchStart":3408.579161,"domainLookupStart":0,"domainLookupEnd":0,"connectStart":0,"connectEnd":0,"secureConnectionStart":0,"requestStart":0,"responseStart":0,"responseEnd":3497.226051,"name":"http://www.google-analytics.com/r/__utm.gif?utmwv=5.6.7&utms=1&utmn=1490710827&utmhn=happia.ru&utmcs=UTF-8&utmsr=1024x768&utmvp=1264x729&utmsc=24-bit&utmul=en-us&utmje=1&utmfl=-&utmdt=%D0%9C%D0%B0%D0%B3%D0%B0%D0%B7%D0%B8%D0%BD%20%C2%AB%D0%A5%D0%B0%D0%BF%D0%BF%D0%B8%D0%B0%C2%BB%20-%20%D0%BA%D0%BE%D1%81%D1%82%D1%8E%D0%BC%D1%8B%20%D0%BD%D0%B0%20%D0%A5%D1%8D%D0%BB%D0%BB%D0%BE%D1%83%D0%B8%D0%BD%2C%20%D0%BC%D0%B0%D1%81%D0%BA%D0%B8%2C%20%D0%B3%D1%80%D0%B8%D0%BC%2C%20%D0%B0%D0%BA%D1%81%D1%81%D0%B5%D1%81%D1%81%D1%83%D0%B0%D1%80%D1%8B%2C%20%D0%BB%D0%B8%D0%BD%D0%B7%D1%8B%2C%20%D1%83%D0%BA%D1%80%D0%B0%D1%88%D0%B5%D0%BD%D0%B8%D1%8F%20%D0%B4%D0%BB%D1%8F%20%D0%A5%D1%8D%D0%BB%D0%BB%D0%BE%D1%83%D0%B8%D0%BD%D0%B0%20%D0%B2%20%D0%9C%D0%BE%D1%81%D0%BA%D0%B2%D0%B5%20%D0%B8%20%D0%A1%D0%B0%D0%BD%D0%BA%D1%82-%D0%9F%D0%B5%D1%82%D0%B5%D1%80%D0%B1%D1%83%D1%80%D0%B3%D0%B5&utmhid=2114251514&utmr=-&utmp=%2F&utmht=1453190825595&utmac=UA-59951424-1&utmcc=__utma%3D48183102.239875234.1453190826.1453190826.1453190826.1%3B%2B__utmz%3D48183102.1453190826.1.1.utmcsr%3D(direct)%7Cutmccn%3D(direct)%7Cutmcmd%3D(none)%3B&utmjid=1204425345&utmredir=1&utmu=qAAAAAAAAAAAAAAAAAAAAAAE~","entryType":"resource","startTime":3408.579161,"duration":88.64688999999998},{"initiatorType":"script","redirectStart":0,"redirectEnd":0,"fetchStart":3423.64856,"domainLookupStart":0,"domainLookupEnd":0,"connectStart":0,"connectEnd":0,"secureConnectionStart":0,"requestStart":0,"responseStart":0,"responseEnd":3507.48656,"name":"http://cdn.mouseflow.com/projects/38fa93aa-8ad0-4949-a10a-644db10d29e5.js","entryType":"resource","startTime":3423.64856,"duration":83.83799999999974},{"initiatorType":"css","redirectStart":0,"redirectEnd":0,"fetchStart":4639.289782,"domainLookupStart":4639.289782,"domainLookupEnd":4639.289782,"connectStart":4639.289782,"connectEnd":4639.289782,"secureConnectionStart":0,"requestStart":4639.532090000001,"responseStart":4781.627055000001,"responseEnd":4781.667823000001,"name":"http://happia.ru/skin/frontend/default/hcp/images/slideshow_arrows.png","entryType":"resource","startTime":4639.289782,"duration":142.37804100000085},{"initiatorType":"img","redirectStart":0,"redirectEnd":0,"fetchStart":4760.20877,"domainLookupStart":0,"domainLookupEnd":0,"connectStart":0,"connectEnd":0,"secureConnectionStart":0,"requestStart":0,"responseStart":0,"responseEnd":4853.447147,"name":"https://mc.yandex.ru/metrika/advert.gif","entryType":"resource","startTime":4760.20877,"duration":93.23837699999967},{"initiatorType":"script","redirectStart":0,"redirectEnd":0,"fetchStart":5850.2236889999995,"domainLookupStart":0,"domainLookupEnd":0,"connectStart":0,"connectEnd":0,"secureConnectionStart":0,"requestStart":0,"responseStart":0,"responseEnd":6061.4314460000005,"name":"https://mc.yandex.ru/watch/26671476?wmode=5&callback=_ymjsp105982092&page-url=http%3A%2F%2Fhappia.ru%2F&browser-info=j%3A1%3As%3A1024x768x24%3Ask%3A1%3Afpr%3A86863607801%3Acn%3A1%3Aw%3A1264x729%3Ai%3A20160119080706%3Aet%3A1453190827%3Aen%3Autf-8%3Av%3A674%3Ac%3A1%3Ala%3Aen-us%3Als%3A1313859933984%3Arqn%3A1%3Arn%3A901583610%3Ahid%3A162973224%3Ads%3A0%2C0%2C286%2C509%2C1%2C0%2C%2C2760%2C190%2C%2C%2C%2C3142%3Awn%3A58952%3Ahl%3A2%3Arqnl%3A1%3Ast%3A1453190827%3Au%3A145319082780666343%3At%3A%D0%9C%D0%B0%D0%B3%D0%B0%D0%B7%D0%B8%D0%BD%20%C2%AB%D0%A5%D0%B0%D0%BF%D0%BF%D0%B8%D0%B0%C2%BB%20-%20%D0%BA%D0%BE%D1%81%D1%82%D1%8E%D0%BC%D1%8B%20%D0%BD%D0%B0%20%D0%A5%D1%8D%D0%BB%D0%BB%D0%BE%D1%83%D0%B8%D0%BD%2C%20%D0%BC%D0%B0%D1%81%D0%BA%D0%B8%2C%20%D0%B3%D1%80%D0%B8%D0%BC%2C%20%D0%B0%D0%BA%D1%81%D1%81%D0%B5%D1%81%D1%81%D1%83%D0%B0%D1%80%D1%8B%2C%20%D0%BB%D0%B8%D0%BD%D0%B7%D1%8B%2C%20%D1%83%D0%BA%D1%80%D0%B0%D1%88%D0%B5%D0%BD%D0%B8%D1%8F%20%D0%B4%D0%BB%D1%8F%20%D0%A5%D1%8D%D0%BB%D0%BB%D0%BE%D1%83%D0%B8%D0%BD%D0%B0%20%D0%B2%20%D0%9C%D0%BE%D1%81%D0%BA%D0%B2%D0%B5%20%D0%B8%20%D0%A1%D0%B0%D0%BD%D0%BA%D1%82-%D0%9F%D0%B5%D1%82%D0%B5%D1%80%D0%B1%D1%83%D1%80%D0%B3%D0%B5","entryType":"resource","startTime":4771.210617000001,"duration":1290.2208289999999},{"initiatorType":"img","redirectStart":0,"redirectEnd":0,"fetchStart":6238.766812,"domainLookupStart":6238.766812,"domainLookupEnd":6238.766812,"connectStart":6238.766812,"connectEnd":6238.766812,"secureConnectionStart":0,"requestStart":6238.950401,"responseStart":6238.766812,"responseEnd":6238.766812,"name":"http://happia.ru/media/product/3b/novogodnii-kostyum-santa-klausa-dlya-malyshki-28.jpg","entryType":"resource","startTime":6238.766812,"duration":0},{"initiatorType":"img","redirectStart":0,"redirectEnd":0,"fetchStart":6239.001391999999,"domainLookupStart":6239.001391999999,"domainLookupEnd":6239.001391999999,"connectStart":6239.001391999999,"connectEnd":6239.001391999999,"secureConnectionStart":0,"requestStart":6239.211326000001,"responseStart":6239.001391999999,"responseEnd":6239.001391999999,"name":"http://happia.ru/media/product/3b/novogodnii-kostyum-santa-klausa-dlya-malyshki-28.jpg","entryType":"resource","startTime":6239.001391999999,"duration":0},{"initiatorType":"img","redirectStart":0,"redirectEnd":0,"fetchStart":6240.3395789999995,"domainLookupStart":6240.3395789999995,"domainLookupEnd":6240.3395789999995,"connectStart":6240.3395789999995,"connectEnd":6240.3395789999995,"secureConnectionStart":0,"requestStart":6240.484708,"responseStart":6240.3395789999995,"responseEnd":6240.3395789999995,"name":"http://happia.ru/media/product/9e/detskii-kostyum-betmena-152-10.jpg","entryType":"resource","startTime":6240.3395789999995,"duration":0},{"initiatorType":"img","redirectStart":0,"redirectEnd":0,"fetchStart":6240.560474999999,"domainLookupStart":6240.560474999999,"domainLookupEnd":6240.560474999999,"connectStart":6240.560474999999,"connectEnd":6240.560474999999,"secureConnectionStart":0,"requestStart":6240.698294000001,"responseStart":6240.560474999999,"responseEnd":6240.560474999999,"name":"http://happia.ru/media/product/88/detskii-kostyum-betmena-140-a3.jpg","entryType":"resource","startTime":6240.560474999999,"duration":0},{"initiatorType":"img","redirectStart":0,"redirectEnd":0,"fetchStart":6240.74953,"domainLookupStart":6240.74953,"domainLookupEnd":6240.74953,"connectStart":6240.74953,"connectEnd":6240.74953,"secureConnectionStart":0,"requestStart":6240.915056000001,"responseStart":6384.072655,"responseEnd":6522.569916,"name":"http://happia.ru/media/product/37/detskii-kostyum-betmena-12.jpg","entryType":"resource","startTime":6240.74953,"duration":281.8203860000003},{"initiatorType":"css","redirectStart":0,"redirectEnd":0,"fetchStart":8316.608248,"domainLookupStart":8316.608248,"domainLookupEnd":8316.608248,"connectStart":8316.608248,"connectEnd":8316.608248,"secureConnectionStart":0,"requestStart":8316.826970999999,"responseStart":8460.421083,"responseEnd":8460.446343,"name":"http://happia.ru/skin/frontend/default/hcp/assets/shadow1.png","entryType":"resource","startTime":8316.608248,"duration":143.83809499999916},{"initiatorType":"css","redirectStart":0,"redirectEnd":0,"fetchStart":8318.116931,"domainLookupStart":8318.116931,"domainLookupEnd":8318.116931,"connectStart":8318.116931,"connectEnd":8318.116931,"secureConnectionStart":0,"requestStart":8318.261095,"responseStart":8459.496224,"responseEnd":8459.54391,"name":"http://happia.ru/skin/frontend/default/hcp/images/opacity_bg.png","entryType":"resource","startTime":8318.116931,"duration":141.42697899999985}],"responsive":true,"speedIndex":4489.911959026645,"timings":{"domainLookupTime":0,"redirectionTime":1,"serverConnectionTime":0,"serverResponseTime":795,"pageDownloadTime":509,"domInteractiveTime":3049,"domContentLoadedTime":3142,"pageLoadTime":6238,"frontEndTime":5442,"backEndTime":287},"userAgent":"Mozilla/5.0 (Macintosh; Intel Mac OS X 10_9_4) AppleWebKit/537.36 (KHTML, like Gecko) Chrome/37.0.2062.120 Safari/537.36","userTimings":{"measures":[],"marks":[]},"windowSize":"1280x729","date":"2016-01-19T08:06:54.944Z"}]},"custom":{"statistics":{},"data":[{}]}}